README.md
setup.py
cli/__init__.py
cli/__main__.py
cli/add_node.py
cli/master_node.py
cli/redis_tool.py
cli/reshard.py
cli/util.py
cli/validate_node.py
redis_cluster_tools.egg-info/PKG-INFO
redis_cluster_tools.egg-info/SOURCES.txt
redis_cluster_tools.egg-info/dependency_links.txt
redis_cluster_tools.egg-info/entry_points.txt
redis_cluster_tools.egg-info/top_level.txt