Metadata-Version: 2.1
Name: redis-cluster-tools
Version: 1
Summary: A small example package
Home-page: https://github.com/AntonAleksandrov13/python-redis-tool.git
Author: Anton Aleksandrov
Author-email: antonaleksandrov24@gmail.com
License: UNKNOWN
Platform: UNKNOWN
Classifier: Programming Language :: Python :: 3
Classifier: License :: OSI Approved :: MIT License
Classifier: Operating System :: OS Independent
